stdpio/__init__.py
stdpio/stdpio.py
stdpio-1.0.0.dist-info/LICENSE
stdpio-1.0.0.dist-info/METADATA
stdpio-1.0.0.dist-info/WHEEL
stdpio-1.0.0.dist-info/top_level.txt
stdpio-1.0.0.dist-info/RECORD
