Metadata-Version: 2.1
Name: stdpio
Version: 1.0.0
Summary: A library to interact with the stdp.io REST API
Home-page: https://stdp.io
Author: stdp
Author-email: info@stdp.io
License: Apache License 2.0
Project-URL: Bug Tracker, https://github.com/stdp/stdpio/issues
Keywords: stdp,stdp.io,neuromorphic,akida,brainchip
Platform: UNKNOWN
Classifier: Programming Language :: Python :: 3
Classifier: License :: OSI Approved :: MIT License
Classifier: Operating System :: OS Independent
Requires-Python: >=3.7
License-File: LICENSE
